Metadata-Version: 2.1
Name: DonBot
Version: 1.1
Summary: Una biblioteca para automatizar pruebas con Selenium, Allure y Behave con python
Home-page: https://github.com/jdas7/DonBot
Download-URL: https://github.com/jdas7/DonBot/tree/1.1
Author: Juan David Alvis Sanchez
Author-email: 
License: MIT
Keywords: testing,logging,example
Requires-Dist: setuptools==69.0.3
Requires-Dist: selenium==4.17.2
Requires-Dist: allure-behave==2.13.2
Requires-Dist: behave==1.2.6
Requires-Dist: requests==2.31.0
